ETMImg2Txt/ImageTextConverter.py
ETMImg2Txt/__init__.py
ETMImg2Txt-0.2.dist-info/LICENSE.txt
ETMImg2Txt-0.2.dist-info/METADATA
ETMImg2Txt-0.2.dist-info/WHEEL
ETMImg2Txt-0.2.dist-info/top_level.txt
ETMImg2Txt-0.2.dist-info/RECORD
